[
null,
{"id":1,"animationId":66,"damage":{"critical":true,"elementId":-1,"formula":"a.atk-b.def","type":1,"variance":20},"description":"主炮开火","effects":[{"code":21,"dataId":15,"value1":0.005,"value2":0},{"code":21,"dataId":4,"value1":0.1,"value2":0},{"code":21,"dataId":5,"value1":0.05,"value2":0},{"code":21,"dataId":8,"value1":0.001,"value2":0}],"hitType":0,"iconIndex":78,"message1":"的主炮开火了","message2":"","mpCost":5,"name":"炮击","note":"","occasion":1,"repeats":1,"requiredWtypeId1":0,"requiredWtypeId2":0,"scope":1,"speed":50,"stypeId":1,"successRate":90,"tpCost":0,"tpGain":0},
{"id":2,"animationId":15,"damage":{"critical":true,"elementId":17,"formula":"a.mat-b.mdf/2","type":1,"variance":50},"description":"","effects":[{"code":21,"dataId":16,"value1":0.8,"value2":0},{"code":21,"dataId":4,"value1":0.01,"value2":0}],"hitType":1,"iconIndex":107,"message1":"发射了鱼雷！","message2":"","mpCost":5,"name":"鱼雷发射","note":"","occasion":1,"repeats":1,"requiredWtypeId1":0,"requiredWtypeId2":0,"scope":1,"speed":50,"stypeId":2,"successRate":90,"tpCost":0,"tpGain":0},
{"id":3,"animationId":-1,"damage":{"critical":true,"elementId":12,"formula":"b.def*2","type":1,"variance":20},"description":"","effects":[{"code":44,"dataId":63,"value1":1,"value2":0}],"hitType":1,"iconIndex":76,"message1":"对敌机射击！","message2":"","mpCost":5,"name":"对空防御","note":"","occasion":1,"repeats":2,"requiredWtypeId1":0,"requiredWtypeId2":0,"scope":0,"speed":50,"stypeId":5,"successRate":95,"tpCost":1,"tpGain":1},
{"id":4,"animationId":65,"damage":{"critical":true,"elementId":1,"formula":"a.mat*10","type":1,"variance":10},"description":"","effects":[],"hitType":2,"iconIndex":76,"message1":"投放了深水炸弹","message2":"","mpCost":50,"name":"投放深水炸弹","note":"","occasion":1,"repeats":1,"requiredWtypeId1":0,"requiredWtypeId2":0,"scope":6,"speed":50,"stypeId":3,"successRate":100,"tpCost":1,"tpGain":1},
{"id":5,"animationId":0,"damage":{"critical":false,"elementId":7,"formula":"a.atk * 4 - b.def * 2","type":0,"variance":20},"description":"","effects":[{"code":21,"dataId":11,"value1":2,"value2":0},{"code":31,"dataId":7,"value1":5,"value2":0}],"hitType":0,"iconIndex":76,"message1":"的攻击！","message2":"","mpCost":5,"name":"潜入水下","note":"","occasion":1,"repeats":1,"requiredWtypeId1":0,"requiredWtypeId2":0,"scope":11,"speed":100,"stypeId":6,"successRate":100,"tpCost":1,"tpGain":20},
{"id":6,"animationId":37,"damage":{"critical":false,"elementId":0,"formula":"0","type":0,"variance":20},"description":"","effects":[{"code":31,"dataId":2,"value1":3,"value2":0},{"code":31,"dataId":4,"value1":3,"value2":0},{"code":31,"dataId":6,"value1":2,"value2":0}],"hitType":0,"iconIndex":26,"message1":"试图负隅顽抗","message2":"","mpCost":10,"name":"负隅顽抗","note":"","occasion":1,"repeats":1,"requiredWtypeId1":0,"requiredWtypeId2":0,"scope":11,"speed":100,"stypeId":9,"successRate":100,"tpCost":0,"tpGain":10},
{"id":7,"animationId":70,"damage":{"critical":true,"elementId":17,"formula":"a.mat-b.mdf","type":1,"variance":20},"description":"","effects":[{"code":21,"dataId":16,"value1":0.5,"value2":0}],"hitType":0,"iconIndex":77,"message1":"正在观望。","message2":"","mpCost":40,"name":"深水鱼雷","note":"","occasion":1,"repeats":1,"requiredWtypeId1":0,"requiredWtypeId2":0,"scope":1,"speed":50,"stypeId":2,"successRate":100,"tpCost":40,"tpGain":0},
{"id":8,"animationId":41,"damage":{"critical":false,"elementId":0,"formula":"a","type":0,"variance":20},"description":"","effects":[{"code":11,"dataId":0,"value1":0.7,"value2":0},{"code":22,"dataId":15,"value1":1,"value2":0},{"code":22,"dataId":16,"value1":1,"value2":0},{"code":22,"dataId":4,"value1":1,"value2":0},{"code":22,"dataId":5,"value1":0.2,"value2":0},{"code":22,"dataId":14,"value1":0.1,"value2":0},{"code":12,"dataId":0,"value1":0.2,"value2":0}],"hitType":0,"iconIndex":221,"message1":"吟唱了%1！","message2":"","mpCost":0,"name":"紧急维修","note":"","occasion":0,"repeats":1,"requiredWtypeId1":0,"requiredWtypeId2":0,"scope":11,"speed":100,"stypeId":10,"successRate":100,"tpCost":0,"tpGain":0},
{"id":9,"animationId":11,"damage":{"critical":true,"elementId":17,"formula":"a.atk-[b.def/2]","type":1,"variance":40},"description":"驱逐型穿甲弹","effects":[{"code":21,"dataId":4,"value1":0.8,"value2":0},{"code":21,"dataId":5,"value1":0.1,"value2":0},{"code":21,"dataId":19,"value1":1.1,"value2":0}],"hitType":0,"iconIndex":113,"message1":"使用了%1！","message2":"","mpCost":5,"name":"穿甲弹","note":"","occasion":1,"repeats":1,"requiredWtypeId1":0,"requiredWtypeId2":0,"scope":1,"speed":50,"stypeId":1,"successRate":90,"tpCost":0,"tpGain":0},
{"id":10,"animationId":68,"damage":{"critical":true,"elementId":-1,"formula":"a.atk-b.def","type":1,"variance":80},"description":"","effects":[{"code":21,"dataId":15,"value1":0.01,"value2":0},{"code":21,"dataId":4,"value1":0.15,"value2":0},{"code":21,"dataId":5,"value1":0.05,"value2":0},{"code":21,"dataId":8,"value1":0.01,"value2":0}],"hitType":1,"iconIndex":78,"message1":"吟唱了%1！","message2":"","mpCost":50,"name":"主炮齐射","note":"","occasion":1,"repeats":2,"requiredWtypeId1":0,"requiredWtypeId2":0,"scope":1,"speed":40,"stypeId":1,"successRate":90,"tpCost":0,"tpGain":0},
{"id":11,"animationId":67,"damage":{"critical":true,"elementId":-1,"formula":"a.atk/2","type":1,"variance":50},"description":"使用副炮进行射击，必要时用于配合主炮辅助射击","effects":[{"code":21,"dataId":4,"value1":0.02,"value2":0},{"code":21,"dataId":15,"value1":0.01,"value2":0}],"hitType":0,"iconIndex":167,"message1":"进行了%1！","message2":"","mpCost":25,"name":"副炮攻击","note":"Flash Damage","occasion":1,"repeats":1,"requiredWtypeId1":0,"requiredWtypeId2":0,"scope":1,"speed":60,"stypeId":4,"successRate":90,"tpCost":0,"tpGain":0},
{"id":12,"animationId":74,"damage":{"critical":false,"elementId":17,"formula":"a.mat-b.mdf/2","type":1,"variance":20},"description":"","effects":[{"code":21,"dataId":16,"value1":0.8,"value2":0}],"hitType":1,"iconIndex":0,"message1":"使用了%1！","message2":"","mpCost":5,"name":"鱼雷齐射","note":"","occasion":1,"repeats":1,"requiredWtypeId1":0,"requiredWtypeId2":0,"scope":5,"speed":50,"stypeId":2,"successRate":80,"tpCost":0,"tpGain":0},
{"id":13,"animationId":0,"damage":{"critical":false,"elementId":0,"formula":"a.def*2","type":1,"variance":20},"description":"","effects":[],"hitType":0,"iconIndex":0,"message1":"","message2":"","mpCost":0,"name":"舰队主炮齐射","note":"","occasion":1,"repeats":1,"requiredWtypeId1":0,"requiredWtypeId2":0,"scope":2,"speed":10,"stypeId":1,"successRate":100,"tpCost":0,"tpGain":0},
{"id":14,"animationId":0,"damage":{"critical":false,"elementId":0,"formula":"a.mat","type":1,"variance":20},"description":"","effects":[],"hitType":0,"iconIndex":0,"message1":"","message2":"","mpCost":0,"name":"舰队鱼雷齐射","note":"","occasion":1,"repeats":1,"requiredWtypeId1":0,"requiredWtypeId2":0,"scope":2,"speed":10,"stypeId":1,"successRate":100,"tpCost":0,"tpGain":0},
{"id":15,"animationId":0,"damage":{"critical":false,"elementId":0,"formula":"v[n]*10","type":1,"variance":20},"description":"","effects":[],"hitType":0,"iconIndex":0,"message1":"","message2":"","mpCost":0,"name":"开幕空袭","note":"","occasion":0,"repeats":1,"requiredWtypeId1":0,"requiredWtypeId2":0,"scope":1,"speed":20,"stypeId":1,"successRate":100,"tpCost":0,"tpGain":0},
{"id":16,"animationId":0,"damage":{"critical":false,"elementId":0,"formula":"a.def*2","type":1,"variance":20},"description":"","effects":[],"hitType":0,"iconIndex":0,"message1":"","message2":"","mpCost":0,"name":"航空攻击","note":"","occasion":0,"repeats":1,"requiredWtypeId1":0,"requiredWtypeId2":0,"scope":1,"speed":0,"stypeId":1,"successRate":100,"tpCost":0,"tpGain":0},
{"id":17,"animationId":0,"damage":{"critical":false,"elementId":1,"formula":"a.def*2","type":1,"variance":20},"description":"","effects":[],"hitType":0,"iconIndex":0,"message1":"","message2":"","mpCost":0,"name":"夜战攻击","note":"","occasion":0,"repeats":1,"requiredWtypeId1":0,"requiredWtypeId2":0,"scope":1,"speed":0,"stypeId":1,"successRate":100,"tpCost":0,"tpGain":0},
{"id":18,"animationId":13,"damage":{"critical":true,"elementId":16,"formula":"2 * a.mat - b.mdf + 100","type":1,"variance":60},"description":"专门破坏上层建筑以及甲板","effects":[{"code":21,"dataId":15,"value1":0.4,"value2":0},{"code":21,"dataId":19,"value1":0.3,"value2":0}],"hitType":0,"iconIndex":0,"message1":"使用了%1！","message2":"","mpCost":10,"name":"高爆弹","note":"","occasion":0,"repeats":1,"requiredWtypeId1":0,"requiredWtypeId2":0,"scope":1,"speed":0,"stypeId":1,"successRate":100,"tpCost":0,"tpGain":0},
{"id":19,"animationId":3,"damage":{"critical":true,"elementId":18,"formula":"0.2 * b.hp + a.mat - b.mdf","type":1,"variance":50},"description":"点燃敌舰，造成5回合的燃烧攻击","effects":[{"code":21,"dataId":15,"value1":0.9,"value2":0},{"code":21,"dataId":19,"value1":0.2,"value2":0},{"code":21,"dataId":4,"value1":0.01,"value2":0},{"code":21,"dataId":5,"value1":0.005,"value2":0}],"hitType":0,"iconIndex":0,"message1":"使用了%1！","message2":"","mpCost":0,"name":"燃烧弹","note":"","occasion":1,"repeats":1,"requiredWtypeId1":0,"requiredWtypeId2":0,"scope":1,"speed":20,"stypeId":1,"successRate":100,"tpCost":0,"tpGain":0},
{"id":20,"animationId":0,"damage":{"critical":false,"elementId":0,"formula":"","type":1,"variance":20},"description":"","effects":[],"hitType":0,"iconIndex":0,"message1":"","message2":"","mpCost":0,"name":"公式","note":"atk 攻击力 def 防御力\nmat 魔法攻击 mdf 魔法防御\nagi 敏捷 luk 幸运\nmhp 最大HP\nmmp 最大MP\nhp HP mp MP tp TP level等级\n","occasion":0,"repeats":1,"requiredWtypeId1":0,"requiredWtypeId2":0,"scope":1,"speed":0,"stypeId":1,"successRate":100,"tpCost":0,"tpGain":0},
{"id":21,"animationId":65,"damage":{"critical":true,"elementId":1,"formula":"a.mat * 9","type":1,"variance":10},"description":"","effects":[],"hitType":0,"iconIndex":76,"message1":"施放了%1！","message2":"","mpCost":50,"name":"深海深水炸弹","note":"","occasion":1,"repeats":1,"requiredWtypeId1":0,"requiredWtypeId2":0,"scope":6,"speed":0,"stypeId":3,"successRate":100,"tpCost":1,"tpGain":0},
{"id":22,"animationId":68,"damage":{"critical":false,"elementId":-1,"formula":"a.atk*2-b.def*2","type":1,"variance":20},"description":"","effects":[],"hitType":0,"iconIndex":78,"message1":"施放了%1！","message2":"","mpCost":5,"name":"深海主炮齐射","note":"","occasion":1,"repeats":1,"requiredWtypeId1":0,"requiredWtypeId2":0,"scope":2,"speed":10,"stypeId":1,"successRate":100,"tpCost":0,"tpGain":0},
{"id":23,"animationId":67,"damage":{"critical":false,"elementId":-1,"formula":"a.def * 2","type":1,"variance":20},"description":"","effects":[],"hitType":0,"iconIndex":0,"message1":"施放了%1！","message2":"","mpCost":0,"name":"深海副炮攻击","note":"","occasion":1,"repeats":1,"requiredWtypeId1":0,"requiredWtypeId2":0,"scope":1,"speed":10,"stypeId":1,"successRate":100,"tpCost":0,"tpGain":0},
{"id":24,"animationId":3,"damage":{"critical":false,"elementId":0,"formula":"100 + a.mdf-b.mdf","type":1,"variance":20},"description":"","effects":[{"code":21,"dataId":15,"value1":0.51,"value2":0},{"code":21,"dataId":19,"value1":0.2,"value2":0}],"hitType":0,"iconIndex":64,"message1":"施放了%1！","message2":"","mpCost":5,"name":"深海燃烧弹","note":"","occasion":1,"repeats":1,"requiredWtypeId1":0,"requiredWtypeId2":0,"scope":1,"speed":0,"stypeId":1,"successRate":100,"tpCost":0,"tpGain":0},
{"id":25,"animationId":0,"damage":{"critical":false,"elementId":0,"formula":"a.def-b.def","type":1,"variance":20},"description":"","effects":[],"hitType":0,"iconIndex":0,"message1":"使用了%1！","message2":"","mpCost":0,"name":"深海舰队主炮齐射","note":"","occasion":1,"repeats":1,"requiredWtypeId1":0,"requiredWtypeId2":0,"scope":2,"speed":0,"stypeId":1,"successRate":100,"tpCost":0,"tpGain":0},
{"id":26,"animationId":0,"damage":{"critical":false,"elementId":0,"formula":"a.def * 2","type":1,"variance":20},"description":"","effects":[],"hitType":0,"iconIndex":0,"message1":"使用了%1！","message2":"","mpCost":0,"name":"深海舰队鱼雷齐射","note":"","occasion":1,"repeats":1,"requiredWtypeId1":0,"requiredWtypeId2":0,"scope":2,"speed":0,"stypeId":1,"successRate":100,"tpCost":0,"tpGain":0},
{"id":27,"animationId":0,"damage":{"critical":false,"elementId":0,"formula":"a.def * 2","type":1,"variance":20},"description":"","effects":[],"hitType":0,"iconIndex":0,"message1":"使用了%1！","message2":"","mpCost":0,"name":"深海开幕空袭","note":"","occasion":0,"repeats":1,"requiredWtypeId1":0,"requiredWtypeId2":0,"scope":2,"speed":0,"stypeId":1,"successRate":100,"tpCost":0,"tpGain":0},
{"id":28,"animationId":0,"damage":{"critical":false,"elementId":0,"formula":"a.def * 2","type":1,"variance":20},"description":"","effects":[],"hitType":0,"iconIndex":0,"message1":"使用了%1！","message2":"","mpCost":0,"name":"深海开幕雷击","note":"","occasion":0,"repeats":1,"requiredWtypeId1":0,"requiredWtypeId2":0,"scope":1,"speed":0,"stypeId":1,"successRate":100,"tpCost":0,"tpGain":0},
{"id":29,"animationId":0,"damage":{"critical":false,"elementId":0,"formula":"a.def * 2","type":1,"variance":20},"description":"","effects":[],"hitType":0,"iconIndex":0,"message1":"使用了%1！","message2":"","mpCost":0,"name":"深海航空攻击","note":"","occasion":0,"repeats":1,"requiredWtypeId1":0,"requiredWtypeId2":0,"scope":1,"speed":0,"stypeId":1,"successRate":100,"tpCost":0,"tpGain":0},
{"id":30,"animationId":0,"damage":{"critical":false,"elementId":0,"formula":"a.def * 2","type":1,"variance":20},"description":"","effects":[],"hitType":0,"iconIndex":0,"message1":"使用了%1！","message2":"","mpCost":0,"name":"深海夜战攻击","note":"","occasion":0,"repeats":1,"requiredWtypeId1":0,"requiredWtypeId2":0,"scope":1,"speed":0,"stypeId":1,"successRate":100,"tpCost":0,"tpGain":0},
{"id":31,"animationId":0,"damage":{"critical":false,"elementId":0,"formula":"0","type":0,"variance":20},"description":"","effects":[],"hitType":0,"iconIndex":0,"message1":"","message2":"","mpCost":0,"name":"","note":"","occasion":0,"repeats":1,"requiredWtypeId1":0,"requiredWtypeId2":0,"scope":1,"speed":0,"stypeId":1,"successRate":100,"tpCost":0,"tpGain":0},
{"id":32,"animationId":40,"damage":{"critical":false,"elementId":0,"formula":"0","type":0,"variance":20},"description":"照亮世界！","effects":[{"code":31,"dataId":7,"value1":5,"value2":0},{"code":31,"dataId":6,"value1":5,"value2":0},{"code":31,"dataId":4,"value1":2,"value2":0}],"hitType":0,"iconIndex":0,"message1":"使用了%1！","message2":"","mpCost":0,"name":"照明弹","note":"","occasion":0,"repeats":1,"requiredWtypeId1":0,"requiredWtypeId2":0,"scope":8,"speed":0,"stypeId":1,"successRate":100,"tpCost":0,"tpGain":0},
{"id":33,"animationId":41,"damage":{"critical":false,"elementId":0,"formula":"200 + a.mat","type":3,"variance":20},"description":"","effects":[{"code":11,"dataId":0,"value1":0.4,"value2":0},{"code":22,"dataId":15,"value1":0.5,"value2":0},{"code":22,"dataId":16,"value1":0.5,"value2":0},{"code":22,"dataId":19,"value1":0.5,"value2":0},{"code":22,"dataId":4,"value1":0.5,"value2":0},{"code":22,"dataId":5,"value1":0.5,"value2":0}],"hitType":0,"iconIndex":221,"message1":"使用了%1！","message2":"","mpCost":10,"name":"舰队维修","note":"","occasion":0,"repeats":1,"requiredWtypeId1":0,"requiredWtypeId2":0,"scope":7,"speed":0,"stypeId":10,"successRate":100,"tpCost":0,"tpGain":1},
{"id":34,"animationId":41,"damage":{"critical":false,"elementId":0,"formula":"200+a.mat","type":3,"variance":20},"description":"","effects":[{"code":11,"dataId":0,"value1":1,"value2":0},{"code":11,"dataId":0,"value1":1,"value2":0},{"code":22,"dataId":15,"value1":1,"value2":0},{"code":22,"dataId":16,"value1":1,"value2":0},{"code":22,"dataId":4,"value1":1,"value2":0},{"code":22,"dataId":12,"value1":1,"value2":0},{"code":22,"dataId":2,"value1":1,"value2":0},{"code":22,"dataId":3,"value1":1,"value2":0},{"code":22,"dataId":1,"value1":1,"value2":0},{"code":22,"dataId":19,"value1":1,"value2":0}],"hitType":0,"iconIndex":221,"message1":"使用了%1！","message2":"","mpCost":5,"name":"紧急维修（女神）","note":"","occasion":1,"repeats":1,"requiredWtypeId1":0,"requiredWtypeId2":0,"scope":9,"speed":100,"stypeId":10,"successRate":100,"tpCost":0,"tpGain":5},
{"id":35,"animationId":0,"damage":{"critical":false,"elementId":0,"formula":"100","type":3,"variance":20},"description":"快速恢复血量和状态，但无法解除大破","effects":[{"code":22,"dataId":2,"value1":1,"value2":0},{"code":22,"dataId":12,"value1":1,"value2":0}],"hitType":0,"iconIndex":221,"message1":"","message2":"","mpCost":0,"name":"破损抢修","note":"","occasion":0,"repeats":1,"requiredWtypeId1":0,"requiredWtypeId2":0,"scope":1,"speed":0,"stypeId":10,"successRate":100,"tpCost":0,"tpGain":0},
{"id":36,"animationId":12,"damage":{"critical":true,"elementId":-1,"formula":"b.adk-a.def/2","type":1,"variance":40},"description":"","effects":[{"code":21,"dataId":4,"value1":0.8,"value2":0},{"code":21,"dataId":5,"value1":0.2,"value2":0},{"code":21,"dataId":19,"value1":1.1,"value2":0},{"code":21,"dataId":3,"value1":0.02,"value2":0},{"code":21,"dataId":3,"value1":0.02,"value2":0},{"code":21,"dataId":3,"value1":0.02,"value2":0}],"hitType":0,"iconIndex":113,"message1":"使用了%1！","message2":"","mpCost":5,"name":"深海穿甲弹","note":"","occasion":1,"repeats":1,"requiredWtypeId1":0,"requiredWtypeId2":0,"scope":1,"speed":50,"stypeId":1,"successRate":100,"tpCost":0,"tpGain":0},
{"id":37,"animationId":0,"damage":{"critical":false,"elementId":0,"formula":"0","type":0,"variance":20},"description":"","effects":[],"hitType":0,"iconIndex":0,"message1":"","message2":"","mpCost":0,"name":"","note":"","occasion":0,"repeats":1,"requiredWtypeId1":0,"requiredWtypeId2":0,"scope":1,"speed":0,"stypeId":1,"successRate":100,"tpCost":0,"tpGain":0},
{"id":38,"animationId":0,"damage":{"critical":false,"elementId":0,"formula":"0","type":0,"variance":20},"description":"随处可用的移动商店","effects":[{"code":44,"dataId":43,"value1":1,"value2":0}],"hitType":0,"iconIndex":0,"message1":"","message2":"","mpCost":0,"name":"移动商店","note":"","occasion":0,"repeats":1,"requiredWtypeId1":0,"requiredWtypeId2":0,"scope":8,"speed":0,"stypeId":10,"successRate":100,"tpCost":0,"tpGain":0},
{"id":39,"animationId":0,"damage":{"critical":false,"elementId":0,"formula":"0","type":0,"variance":20},"description":"","effects":[],"hitType":0,"iconIndex":0,"message1":"","message2":"","mpCost":0,"name":"","note":"","occasion":0,"repeats":1,"requiredWtypeId1":0,"requiredWtypeId2":0,"scope":1,"speed":0,"stypeId":1,"successRate":100,"tpCost":0,"tpGain":0},
{"id":40,"animationId":0,"damage":{"critical":false,"elementId":0,"formula":"0","type":0,"variance":20},"description":"5回合内强化所有数值，并免疫沉没","effects":[{"code":31,"dataId":2,"value1":5,"value2":0},{"code":31,"dataId":3,"value1":5,"value2":0},{"code":31,"dataId":4,"value1":5,"value2":0},{"code":31,"dataId":5,"value1":5,"value2":0},{"code":31,"dataId":6,"value1":5,"value2":0},{"code":31,"dataId":7,"value1":5,"value2":0},{"code":31,"dataId":0,"value1":5,"value2":0},{"code":31,"dataId":1,"value1":5,"value2":0},{"code":21,"dataId":60,"value1":1,"value2":0}],"hitType":0,"iconIndex":21,"message1":"进入了%1！","message2":"","mpCost":20,"name":"鬼神模式","note":"","occasion":1,"repeats":1,"requiredWtypeId1":0,"requiredWtypeId2":0,"scope":11,"speed":2000,"stypeId":1,"successRate":100,"tpCost":10,"tpGain":0},
{"id":41,"animationId":79,"damage":{"critical":false,"elementId":-1,"formula":"a.atk-b.def","type":1,"variance":20},"description":"巴达利亚炮击","effects":[],"hitType":0,"iconIndex":78,"message1":"的主炮开火了","message2":"","mpCost":10,"name":"主炮开火","note":"","occasion":1,"repeats":1,"requiredWtypeId1":0,"requiredWtypeId2":0,"scope":1,"speed":50,"stypeId":1,"successRate":80,"tpCost":0,"tpGain":1},
{"id":42,"animationId":0,"damage":{"critical":false,"elementId":0,"formula":"0","type":0,"variance":20},"description":"","effects":[],"hitType":0,"iconIndex":0,"message1":"","message2":"","mpCost":0,"name":"","note":"","occasion":0,"repeats":1,"requiredWtypeId1":0,"requiredWtypeId2":0,"scope":1,"speed":0,"stypeId":1,"successRate":100,"tpCost":0,"tpGain":0},
{"id":43,"animationId":89,"damage":{"critical":true,"elementId":9,"formula":"if (!a.isStateAffected(30)) a.addState(30); 300","type":1,"variance":50},"description":"","effects":[{"code":21,"dataId":16,"value1":0.8,"value2":0}],"hitType":2,"iconIndex":0,"message1":"使用了%1！","message2":"","mpCost":0,"name":"深海舰攻鱼雷投射","note":"","occasion":1,"repeats":1,"requiredWtypeId1":0,"requiredWtypeId2":0,"scope":2,"speed":0,"stypeId":8,"successRate":90,"tpCost":0,"tpGain":0},
{"id":44,"animationId":0,"damage":{"critical":false,"elementId":0,"formula":"a.def * 2","type":0,"variance":20},"description":"","effects":[{"code":21,"dataId":28,"value1":1,"value2":0}],"hitType":0,"iconIndex":0,"message1":"的%1了！","message2":"","mpCost":0,"name":"深海舰攻起飞","note":"","occasion":1,"repeats":1,"requiredWtypeId1":0,"requiredWtypeId2":0,"scope":11,"speed":10,"stypeId":7,"successRate":100,"tpCost":0,"tpGain":0},
{"id":45,"animationId":0,"damage":{"critical":false,"elementId":17,"formula":"if (!a.isStateAffected(30)) a.addState(30); 300","type":1,"variance":20},"description":"","effects":[{"code":21,"dataId":15,"value1":0.8,"value2":0}],"hitType":2,"iconIndex":0,"message1":"使用了%1！","message2":"","mpCost":0,"name":"深海舰爆航弹投射","note":"","occasion":1,"repeats":1,"requiredWtypeId1":0,"requiredWtypeId2":0,"scope":2,"speed":0,"stypeId":8,"successRate":100,"tpCost":0,"tpGain":0},
{"id":46,"animationId":0,"damage":{"critical":false,"elementId":0,"formula":"0","type":0,"variance":20},"description":"","effects":[],"hitType":0,"iconIndex":0,"message1":"","message2":"","mpCost":0,"name":"深海舰爆起飞","note":"","occasion":1,"repeats":1,"requiredWtypeId1":0,"requiredWtypeId2":0,"scope":11,"speed":0,"stypeId":7,"successRate":100,"tpCost":0,"tpGain":0},
{"id":47,"animationId":0,"damage":{"critical":false,"elementId":0,"formula":"B.V[150]","type":0,"variance":20},"description":"","effects":[],"hitType":0,"iconIndex":0,"message1":"开始%1！","message2":"","mpCost":0,"name":"抢夺制空权","note":"","occasion":1,"repeats":1,"requiredWtypeId1":0,"requiredWtypeId2":0,"scope":2,"speed":0,"stypeId":1,"successRate":100,"tpCost":0,"tpGain":0},
{"id":48,"animationId":0,"damage":{"critical":false,"elementId":0,"formula":"0","type":0,"variance":20},"description":"","effects":[],"hitType":0,"iconIndex":0,"message1":"","message2":"","mpCost":0,"name":"深海舰战起飞","note":"","occasion":1,"repeats":1,"requiredWtypeId1":0,"requiredWtypeId2":0,"scope":11,"speed":0,"stypeId":7,"successRate":100,"tpCost":0,"tpGain":0},
{"id":49,"animationId":0,"damage":{"critical":false,"elementId":0,"formula":"0","type":1,"variance":20},"description":"","effects":[],"hitType":0,"iconIndex":0,"message1":"使用了%1！","message2":"","mpCost":0,"name":"对舰扫射","note":"","occasion":1,"repeats":1,"requiredWtypeId1":0,"requiredWtypeId2":0,"scope":1,"speed":0,"stypeId":1,"successRate":100,"tpCost":0,"tpGain":0},
{"id":50,"animationId":0,"damage":{"critical":false,"elementId":0,"formula":"0","type":0,"variance":20},"description":"","effects":[],"hitType":0,"iconIndex":0,"message1":"","message2":"","mpCost":0,"name":"","note":"","occasion":0,"repeats":1,"requiredWtypeId1":0,"requiredWtypeId2":0,"scope":1,"speed":0,"stypeId":1,"successRate":100,"tpCost":0,"tpGain":0},
{"id":51,"animationId":0,"damage":{"critical":false,"elementId":0,"formula":"0","type":0,"variance":20},"description":"","effects":[],"hitType":0,"iconIndex":0,"message1":"","message2":"","mpCost":0,"name":"舰载机弹药补充","note":"","occasion":1,"repeats":1,"requiredWtypeId1":0,"requiredWtypeId2":0,"scope":11,"speed":0,"stypeId":1,"successRate":100,"tpCost":0,"tpGain":0},
{"id":52,"animationId":0,"damage":{"critical":false,"elementId":0,"formula":"0","type":0,"variance":20},"description":"","effects":[],"hitType":0,"iconIndex":0,"message1":"","message2":"","mpCost":0,"name":"","note":"","occasion":0,"repeats":1,"requiredWtypeId1":0,"requiredWtypeId2":0,"scope":1,"speed":0,"stypeId":1,"successRate":100,"tpCost":0,"tpGain":0},
{"id":53,"animationId":84,"damage":{"critical":false,"elementId":7,"formula":"[a.atk-b.def]*2","type":1,"variance":20},"description":"北方1","effects":[],"hitType":0,"iconIndex":0,"message1":"施放了%1！","message2":"","mpCost":0,"name":"深海炮击","note":"","occasion":0,"repeats":1,"requiredWtypeId1":0,"requiredWtypeId2":0,"scope":1,"speed":0,"stypeId":4,"successRate":100,"tpCost":0,"tpGain":0},
{"id":54,"animationId":85,"damage":{"critical":false,"elementId":7,"formula":"a.atk-b.def","type":1,"variance":20},"description":"北方2","effects":[],"hitType":0,"iconIndex":0,"message1":"施放了%1！","message2":"","mpCost":0,"name":"深海炮击","note":"","occasion":0,"repeats":1,"requiredWtypeId1":0,"requiredWtypeId2":0,"scope":1,"speed":0,"stypeId":4,"successRate":100,"tpCost":0,"tpGain":0},
{"id":55,"animationId":86,"damage":{"critical":false,"elementId":0,"formula":"a.def * 2","type":1,"variance":20},"description":"","effects":[{"code":21,"dataId":28,"value1":1,"value2":0}],"hitType":0,"iconIndex":0,"message1":"深海舰攻起飞了！","message2":"","mpCost":0,"name":"深海舰攻起飞","note":"","occasion":1,"repeats":1,"requiredWtypeId1":0,"requiredWtypeId2":0,"scope":11,"speed":10,"stypeId":7,"successRate":100,"tpCost":0,"tpGain":0},
{"id":56,"animationId":0,"damage":{"critical":true,"elementId":7,"formula":"1000-b.def","type":1,"variance":50},"description":"小北方竭尽全力的炮击","effects":[],"hitType":0,"iconIndex":0,"message1":"小北方竭尽全力的炮击","message2":"","mpCost":0,"name":"北方炮击","note":"","occasion":1,"repeats":1,"requiredWtypeId1":0,"requiredWtypeId2":0,"scope":2,"speed":0,"stypeId":1,"successRate":100,"tpCost":0,"tpGain":0},
{"id":57,"animationId":87,"damage":{"critical":false,"elementId":0,"formula":"a.def * 2","type":0,"variance":20},"description":"","effects":[{"code":21,"dataId":28,"value1":1,"value2":0}],"hitType":0,"iconIndex":0,"message1":"深海舰攻起飞了！","message2":"","mpCost":0,"name":"深海舰攻起飞","note":"","occasion":1,"repeats":1,"requiredWtypeId1":0,"requiredWtypeId2":0,"scope":11,"speed":10,"stypeId":7,"successRate":100,"tpCost":0,"tpGain":0},
{"id":58,"animationId":0,"damage":{"critical":false,"elementId":0,"formula":"0","type":0,"variance":20},"description":"","effects":[],"hitType":0,"iconIndex":0,"message1":"","message2":"","mpCost":0,"name":"","note":"","occasion":0,"repeats":1,"requiredWtypeId1":0,"requiredWtypeId2":0,"scope":1,"speed":0,"stypeId":1,"successRate":100,"tpCost":0,"tpGain":0},
{"id":59,"animationId":89,"damage":{"critical":true,"elementId":9,"formula":"if (!a.isStateAffected(40)) a.addState(40);300-b.def","type":1,"variance":80},"description":"飞机水平投射鱼雷。","effects":[{"code":21,"dataId":16,"value1":0.8,"value2":0},{"code":44,"dataId":77,"value1":1,"value2":0}],"hitType":0,"iconIndex":0,"message1":"使用了%1！","message2":"","mpCost":0,"name":"舰攻鱼雷投射","note":"","occasion":1,"repeats":1,"requiredWtypeId1":0,"requiredWtypeId2":0,"scope":1,"speed":0,"stypeId":8,"successRate":100,"tpCost":0,"tpGain":0},
{"id":60,"animationId":91,"damage":{"critical":false,"elementId":0,"formula":"a.def * 2","type":0,"variance":20},"description":"","effects":[{"code":21,"dataId":38,"value1":1,"value2":0}],"hitType":0,"iconIndex":0,"message1":"的%1了！","message2":"","mpCost":0,"name":"舰攻起飞","note":"","occasion":1,"repeats":1,"requiredWtypeId1":0,"requiredWtypeId2":0,"scope":11,"speed":10,"stypeId":7,"successRate":100,"tpCost":0,"tpGain":0},
{"id":61,"animationId":0,"damage":{"critical":false,"elementId":9,"formula":"a.atk-b.def/2","type":1,"variance":20},"description":"舰载轰炸机水平轰炸","effects":[{"code":21,"dataId":15,"value1":0.5,"value2":0},{"code":21,"dataId":19,"value1":0.45,"value2":0},{"code":44,"dataId":78,"value1":1,"value2":0}],"hitType":0,"iconIndex":0,"message1":"使用了%1！","message2":"","mpCost":0,"name":"舰爆航弹投射-水平投射","note":"","occasion":1,"repeats":1,"requiredWtypeId1":0,"requiredWtypeId2":0,"scope":2,"speed":0,"stypeId":8,"successRate":100,"tpCost":0,"tpGain":0},
{"id":62,"animationId":92,"damage":{"critical":false,"elementId":0,"formula":"0","type":0,"variance":20},"description":"","effects":[{"code":21,"dataId":41,"value1":1,"value2":0}],"hitType":0,"iconIndex":0,"message1":"的%1了！","message2":"","mpCost":0,"name":"舰爆起飞","note":"","occasion":1,"repeats":1,"requiredWtypeId1":0,"requiredWtypeId2":0,"scope":11,"speed":0,"stypeId":7,"successRate":100,"tpCost":0,"tpGain":0},
{"id":63,"animationId":0,"damage":{"critical":false,"elementId":0,"formula":"B.V[150]","type":0,"variance":20},"description":"","effects":[{"code":44,"dataId":64,"value1":1,"value2":0}],"hitType":0,"iconIndex":0,"message1":"开始%1！","message2":"","mpCost":0,"name":"抢夺制空权","note":"","occasion":1,"repeats":1,"requiredWtypeId1":0,"requiredWtypeId2":0,"scope":2,"speed":0,"stypeId":1,"successRate":100,"tpCost":0,"tpGain":0},
{"id":64,"animationId":93,"damage":{"critical":false,"elementId":0,"formula":"0","type":0,"variance":20},"description":"","effects":[{"code":21,"dataId":43,"value1":1,"value2":0}],"hitType":0,"iconIndex":0,"message1":"的%1了！","message2":"","mpCost":0,"name":"舰战起飞","note":"","occasion":1,"repeats":1,"requiredWtypeId1":0,"requiredWtypeId2":0,"scope":11,"speed":0,"stypeId":7,"successRate":100,"tpCost":0,"tpGain":0},
{"id":65,"animationId":0,"damage":{"critical":false,"elementId":0,"formula":"100","type":1,"variance":20},"description":"","effects":[{"code":44,"dataId":79,"value1":1,"value2":0}],"hitType":0,"iconIndex":0,"message1":"使用了%1！","message2":"","mpCost":0,"name":"对舰扫射","note":"","occasion":1,"repeats":1,"requiredWtypeId1":0,"requiredWtypeId2":0,"scope":1,"speed":0,"stypeId":1,"successRate":100,"tpCost":0,"tpGain":0},
{"id":66,"animationId":0,"damage":{"critical":false,"elementId":0,"formula":"0","type":0,"variance":20},"description":"","effects":[],"hitType":0,"iconIndex":0,"message1":"","message2":"","mpCost":0,"name":"舰载机弹药补充","note":"","occasion":1,"repeats":1,"requiredWtypeId1":0,"requiredWtypeId2":0,"scope":11,"speed":0,"stypeId":1,"successRate":100,"tpCost":0,"tpGain":0},
{"id":67,"animationId":0,"damage":{"critical":false,"elementId":9,"formula":"[a.atk-b.def]*2","type":1,"variance":20},"description":"飞机沿陡峭角度向下俯冲，飞到目标很近的地方时投弹。\n命中概率大，伤害较高。","effects":[{"code":21,"dataId":15,"value1":0.4,"value2":0},{"code":21,"dataId":19,"value1":0.45,"value2":0},{"code":21,"dataId":8,"value1":0.1,"value2":0},{"code":44,"dataId":78,"value1":1,"value2":0}],"hitType":1,"iconIndex":0,"message1":"使用了俯冲轰炸","message2":"","mpCost":0,"name":"舰爆航弹投射-俯冲","note":"","occasion":1,"repeats":1,"requiredWtypeId1":0,"requiredWtypeId2":0,"scope":2,"speed":0,"stypeId":8,"successRate":90,"tpCost":0,"tpGain":0},
{"id":68,"animationId":0,"damage":{"critical":false,"elementId":9,"formula":"a.atk-b.def/2","type":1,"variance":20},"description":"飞机沿小角度下滑角进入，接近目标时改平飞投弹。\n精度不高，炸弹动能也不大，但非常节省燃料","effects":[{"code":44,"dataId":78,"value1":1,"value2":0}],"hitType":1,"iconIndex":0,"message1":"使用了下滑轰炸","message2":"","mpCost":10,"name":"舰爆航弹投射-下滑轰炸","note":"","occasion":1,"repeats":1,"requiredWtypeId1":0,"requiredWtypeId2":0,"scope":1,"speed":0,"stypeId":8,"successRate":40,"tpCost":0,"tpGain":0},
{"id":69,"animationId":0,"damage":{"critical":true,"elementId":9,"formula":"a.atk*3-b.def","type":1,"variance":80},"description":"轰炸机在极高的空中进行投弹。\n命中看天，但一发入魂","effects":[{"code":21,"dataId":3,"value1":0.79,"value2":0},{"code":44,"dataId":78,"value1":1,"value2":0}],"hitType":1,"iconIndex":0,"message1":"使用了高空轰炸","message2":"","mpCost":10,"name":"舰爆航弹投射-高空轰炸","note":"","occasion":1,"repeats":1,"requiredWtypeId1":0,"requiredWtypeId2":0,"scope":1,"speed":0,"stypeId":8,"successRate":30,"tpCost":0,"tpGain":0},
{"id":70,"animationId":0,"damage":{"critical":false,"elementId":6,"formula":"2000","type":1,"variance":80},"description":"发动无脑的自杀冲锋。\n杀敌一千，自损一万。","effects":[{"code":44,"dataId":65,"value1":1,"value2":0}],"hitType":0,"iconIndex":78,"message1":"发动了自杀攻击","message2":"真是灭绝人性!","mpCost":0,"name":"舰爆航弹投射-自杀攻击","note":"","occasion":1,"repeats":1,"requiredWtypeId1":0,"requiredWtypeId2":0,"scope":1,"speed":0,"stypeId":8,"successRate":100,"tpCost":0,"tpGain":0},
{"id":71,"animationId":0,"damage":{"critical":false,"elementId":0,"formula":"0","type":0,"variance":20},"description":"","effects":[],"hitType":0,"iconIndex":0,"message1":"","message2":"","mpCost":0,"name":"--------------","note":"","occasion":0,"repeats":1,"requiredWtypeId1":0,"requiredWtypeId2":0,"scope":1,"speed":0,"stypeId":1,"successRate":100,"tpCost":0,"tpGain":0},
{"id":72,"animationId":0,"damage":{"critical":false,"elementId":0,"formula":"0","type":0,"variance":20},"description":"将身体贴在舰娘的背后以阻挡敌人的炮火\n多损啊····","effects":[{"code":21,"dataId":55,"value1":1,"value2":0}],"hitType":0,"iconIndex":82,"message1":"躲在舰娘后面瑟瑟发抖","message2":"提督你也太逊了··","mpCost":0,"name":"躲避","note":"","occasion":1,"repeats":1,"requiredWtypeId1":0,"requiredWtypeId2":0,"scope":7,"speed":0,"stypeId":11,"successRate":100,"tpCost":0,"tpGain":0},
{"id":73,"animationId":0,"damage":{"critical":false,"elementId":0,"formula":"0","type":0,"variance":20},"description":"把舰娘拉到自己面前来阻挡敌人的炮火。\n太贱了···","effects":[{"code":21,"dataId":56,"value1":1,"value2":0}],"hitType":0,"iconIndex":82,"message1":"把舰娘拉到自己面前了","message2":"提督你要干什么？？","mpCost":0,"name":"规避","note":"","occasion":1,"repeats":1,"requiredWtypeId1":0,"requiredWtypeId2":0,"scope":11,"speed":0,"stypeId":11,"successRate":100,"tpCost":0,"tpGain":0},
{"id":74,"animationId":0,"damage":{"critical":false,"elementId":0,"formula":"0","type":0,"variance":20},"description":"帮舰娘阻挡一次伤害（当然你大概率会死）","effects":[{"code":21,"dataId":58,"value1":1,"value2":0},{"code":32,"dataId":3,"value1":1,"value2":0},{"code":32,"dataId":5,"value1":1,"value2":0}],"hitType":0,"iconIndex":81,"message1":"挡在了舰娘的面前","message2":"","mpCost":0,"name":"以身为盾","note":"<Physical Taunt>\n<Magical Taunt>\n<Certain Taunt> ","occasion":0,"repeats":1,"requiredWtypeId1":0,"requiredWtypeId2":0,"scope":7,"speed":0,"stypeId":11,"successRate":100,"tpCost":0,"tpGain":0},
{"id":75,"animationId":0,"damage":{"critical":false,"elementId":0,"formula":"0","type":0,"variance":20},"description":"来自某金发吸血鬼的真传。\n免疫所有伤害和效果。（包括这个技能）","effects":[{"code":21,"dataId":53,"value1":1,"value2":0}],"hitType":0,"iconIndex":81,"message1":"","message2":"","mpCost":0,"name":"抱头蹲防","note":"","occasion":0,"repeats":1,"requiredWtypeId1":0,"requiredWtypeId2":0,"scope":11,"speed":2000,"stypeId":11,"successRate":100,"tpCost":0,"tpGain":0},
{"id":76,"animationId":0,"damage":{"critical":false,"elementId":0,"formula":"0","type":0,"variance":20},"description":"通过判断敌人的弹道而进行紧急制动来躲避敌人的炮弹","effects":[{"code":21,"dataId":55,"value1":1,"value2":0}],"hitType":0,"iconIndex":82,"message1":"正在摆动船身","message2":"","mpCost":0,"name":"规避","note":"","occasion":1,"repeats":1,"requiredWtypeId1":0,"requiredWtypeId2":0,"scope":11,"speed":0,"stypeId":11,"successRate":100,"tpCost":0,"tpGain":0},
{"id":77,"animationId":0,"damage":{"critical":false,"elementId":0,"formula":"200","type":1,"variance":20},"description":"深海托起她厚重的“装甲”讥讽着，这会引起除战列舰\n以外的舰娘造成精神冲击","effects":[{"code":21,"dataId":9,"value1":0.2,"value2":0},{"code":21,"dataId":8,"value1":0.1,"value2":0}],"hitType":1,"iconIndex":0,"message1":"","message2":"","mpCost":0,"name":"嘲笑","note":"","occasion":0,"repeats":1,"requiredWtypeId1":0,"requiredWtypeId2":0,"scope":1,"speed":0,"stypeId":1,"successRate":80,"tpCost":0,"tpGain":0},
{"id":78,"animationId":15,"damage":{"critical":true,"elementId":17,"formula":"a.mat-b.mdf/2","type":1,"variance":50},"description":"","effects":[{"code":21,"dataId":16,"value1":0.8,"value2":0},{"code":21,"dataId":4,"value1":0.01,"value2":0}],"hitType":1,"iconIndex":107,"message1":"发射了鱼雷！","message2":"","mpCost":5,"name":"鱼雷发射","note":"","occasion":1,"repeats":1,"requiredWtypeId1":0,"requiredWtypeId2":0,"scope":1,"speed":50,"stypeId":2,"successRate":90,"tpCost":0,"tpGain":0},
{"id":79,"animationId":0,"damage":{"critical":false,"elementId":0,"formula":"0","type":1,"variance":20},"description":"连续对敌舰高速射击，但有一定程度导致卡壳\n而无法射击","effects":[{"code":11,"dataId":0,"value1":0.2,"value2":0}],"hitType":0,"iconIndex":0,"message1":"","message2":"","mpCost":0,"name":"高速装填","note":"","occasion":0,"repeats":1,"requiredWtypeId1":0,"requiredWtypeId2":0,"scope":1,"speed":50,"stypeId":1,"successRate":100,"tpCost":0,"tpGain":0},
{"id":80,"animationId":0,"damage":{"critical":false,"elementId":0,"formula":"0","type":0,"variance":20},"description":"","effects":[],"hitType":0,"iconIndex":0,"message1":"","message2":"","mpCost":0,"name":"","note":"","occasion":0,"repeats":1,"requiredWtypeId1":0,"requiredWtypeId2":0,"scope":1,"speed":0,"stypeId":1,"successRate":100,"tpCost":0,"tpGain":0},
{"id":81,"animationId":0,"damage":{"critical":true,"elementId":17,"formula":"a.mat-b.mdf/2","type":0,"variance":50},"description":"","effects":[{"code":21,"dataId":55,"value1":1,"value2":0}],"hitType":0,"iconIndex":0,"message1":"","message2":"","mpCost":5,"name":"规避","note":"","occasion":1,"repeats":1,"requiredWtypeId1":0,"requiredWtypeId2":0,"scope":11,"speed":2000,"stypeId":0,"successRate":90,"tpCost":0,"tpGain":0},
{"id":82,"animationId":0,"damage":{"critical":false,"elementId":0,"formula":"0","type":0,"variance":20},"description":"","effects":[],"hitType":0,"iconIndex":0,"message1":"","message2":"","mpCost":0,"name":"","note":"","occasion":0,"repeats":1,"requiredWtypeId1":0,"requiredWtypeId2":0,"scope":1,"speed":0,"stypeId":1,"successRate":100,"tpCost":0,"tpGain":0},
{"id":83,"animationId":0,"damage":{"critical":false,"elementId":0,"formula":"0","type":0,"variance":20},"description":"","effects":[],"hitType":0,"iconIndex":0,"message1":"","message2":"","mpCost":0,"name":"","note":"","occasion":0,"repeats":1,"requiredWtypeId1":0,"requiredWtypeId2":0,"scope":1,"speed":0,"stypeId":1,"successRate":100,"tpCost":0,"tpGain":0},
{"id":84,"animationId":0,"damage":{"critical":false,"elementId":0,"formula":"0","type":0,"variance":20},"description":"","effects":[],"hitType":0,"iconIndex":0,"message1":"","message2":"","mpCost":0,"name":"","note":"","occasion":0,"repeats":1,"requiredWtypeId1":0,"requiredWtypeId2":0,"scope":1,"speed":0,"stypeId":1,"successRate":100,"tpCost":0,"tpGain":0},
{"id":85,"animationId":0,"damage":{"critical":false,"elementId":0,"formula":"0","type":0,"variance":20},"description":"","effects":[],"hitType":0,"iconIndex":0,"message1":"","message2":"","mpCost":0,"name":"","note":"","occasion":0,"repeats":1,"requiredWtypeId1":0,"requiredWtypeId2":0,"scope":1,"speed":0,"stypeId":1,"successRate":100,"tpCost":0,"tpGain":0},
{"id":86,"animationId":0,"damage":{"critical":false,"elementId":0,"formula":"0","type":0,"variance":20},"description":"","effects":[],"hitType":0,"iconIndex":0,"message1":"","message2":"","mpCost":0,"name":"","note":"","occasion":0,"repeats":1,"requiredWtypeId1":0,"requiredWtypeId2":0,"scope":1,"speed":0,"stypeId":1,"successRate":100,"tpCost":0,"tpGain":0},
{"id":87,"animationId":0,"damage":{"critical":false,"elementId":0,"formula":"0","type":0,"variance":20},"description":"","effects":[],"hitType":0,"iconIndex":0,"message1":"","message2":"","mpCost":0,"name":"","note":"","occasion":0,"repeats":1,"requiredWtypeId1":0,"requiredWtypeId2":0,"scope":1,"speed":0,"stypeId":1,"successRate":100,"tpCost":0,"tpGain":0},
{"id":88,"animationId":0,"damage":{"critical":false,"elementId":0,"formula":"0","type":0,"variance":20},"description":"","effects":[],"hitType":0,"iconIndex":0,"message1":"","message2":"","mpCost":0,"name":"","note":"","occasion":0,"repeats":1,"requiredWtypeId1":0,"requiredWtypeId2":0,"scope":1,"speed":0,"stypeId":1,"successRate":100,"tpCost":0,"tpGain":0},
{"id":89,"animationId":0,"damage":{"critical":false,"elementId":0,"formula":"0","type":0,"variance":20},"description":"","effects":[],"hitType":0,"iconIndex":0,"message1":"","message2":"","mpCost":0,"name":"","note":"","occasion":0,"repeats":1,"requiredWtypeId1":0,"requiredWtypeId2":0,"scope":1,"speed":0,"stypeId":1,"successRate":100,"tpCost":0,"tpGain":0},
{"id":90,"animationId":0,"damage":{"critical":false,"elementId":0,"formula":"0","type":0,"variance":20},"description":"","effects":[],"hitType":0,"iconIndex":0,"message1":"","message2":"","mpCost":0,"name":"","note":"","occasion":0,"repeats":1,"requiredWtypeId1":0,"requiredWtypeId2":0,"scope":1,"speed":0,"stypeId":1,"successRate":100,"tpCost":0,"tpGain":0},
{"id":91,"animationId":0,"damage":{"critical":false,"elementId":0,"formula":"0","type":0,"variance":20},"description":"","effects":[],"hitType":0,"iconIndex":0,"message1":"","message2":"","mpCost":0,"name":"","note":"","occasion":0,"repeats":1,"requiredWtypeId1":0,"requiredWtypeId2":0,"scope":1,"speed":0,"stypeId":1,"successRate":100,"tpCost":0,"tpGain":0},
{"id":92,"animationId":0,"damage":{"critical":false,"elementId":0,"formula":"0","type":0,"variance":20},"description":"","effects":[],"hitType":0,"iconIndex":0,"message1":"","message2":"","mpCost":0,"name":"","note":"","occasion":0,"repeats":1,"requiredWtypeId1":0,"requiredWtypeId2":0,"scope":1,"speed":0,"stypeId":1,"successRate":100,"tpCost":0,"tpGain":0},
{"id":93,"animationId":0,"damage":{"critical":false,"elementId":0,"formula":"0","type":0,"variance":20},"description":"","effects":[],"hitType":0,"iconIndex":0,"message1":"","message2":"","mpCost":0,"name":"","note":"","occasion":0,"repeats":1,"requiredWtypeId1":0,"requiredWtypeId2":0,"scope":1,"speed":0,"stypeId":1,"successRate":100,"tpCost":0,"tpGain":0},
{"id":94,"animationId":0,"damage":{"critical":false,"elementId":0,"formula":"0","type":0,"variance":20},"description":"","effects":[],"hitType":0,"iconIndex":0,"message1":"","message2":"","mpCost":0,"name":"","note":"","occasion":0,"repeats":1,"requiredWtypeId1":0,"requiredWtypeId2":0,"scope":1,"speed":0,"stypeId":1,"successRate":100,"tpCost":0,"tpGain":0},
{"id":95,"animationId":0,"damage":{"critical":false,"elementId":0,"formula":"0","type":0,"variance":20},"description":"","effects":[],"hitType":0,"iconIndex":0,"message1":"","message2":"","mpCost":0,"name":"","note":"","occasion":0,"repeats":1,"requiredWtypeId1":0,"requiredWtypeId2":0,"scope":1,"speed":0,"stypeId":1,"successRate":100,"tpCost":0,"tpGain":0},
{"id":96,"animationId":0,"damage":{"critical":false,"elementId":0,"formula":"0","type":0,"variance":20},"description":"","effects":[],"hitType":0,"iconIndex":0,"message1":"","message2":"","mpCost":0,"name":"","note":"","occasion":0,"repeats":1,"requiredWtypeId1":0,"requiredWtypeId2":0,"scope":1,"speed":0,"stypeId":1,"successRate":100,"tpCost":0,"tpGain":0},
{"id":97,"animationId":0,"damage":{"critical":false,"elementId":0,"formula":"0","type":0,"variance":20},"description":"","effects":[],"hitType":0,"iconIndex":0,"message1":"","message2":"","mpCost":0,"name":"","note":"","occasion":0,"repeats":1,"requiredWtypeId1":0,"requiredWtypeId2":0,"scope":1,"speed":0,"stypeId":1,"successRate":100,"tpCost":0,"tpGain":0},
{"id":98,"animationId":0,"damage":{"critical":false,"elementId":0,"formula":"0","type":0,"variance":20},"description":"","effects":[],"hitType":0,"iconIndex":0,"message1":"","message2":"","mpCost":0,"name":"","note":"","occasion":0,"repeats":1,"requiredWtypeId1":0,"requiredWtypeId2":0,"scope":1,"speed":0,"stypeId":1,"successRate":100,"tpCost":0,"tpGain":0},
{"id":99,"animationId":0,"damage":{"critical":false,"elementId":0,"formula":"0","type":0,"variance":20},"description":"","effects":[],"hitType":0,"iconIndex":0,"message1":"","message2":"","mpCost":0,"name":"","note":"","occasion":0,"repeats":1,"requiredWtypeId1":0,"requiredWtypeId2":0,"scope":1,"speed":0,"stypeId":1,"successRate":100,"tpCost":0,"tpGain":0},
{"id":100,"animationId":0,"damage":{"critical":false,"elementId":0,"formula":"0","type":0,"variance":20},"description":"","effects":[],"hitType":0,"iconIndex":0,"message1":"","message2":"","mpCost":0,"name":"","note":"","occasion":0,"repeats":1,"requiredWtypeId1":0,"requiredWtypeId2":0,"scope":1,"speed":0,"stypeId":1,"successRate":100,"tpCost":0,"tpGain":0}
]